[
  {
    "match_id":1913898,
    "team_side":"away",
    "team_id":833,
    "period":16,
    "start_minute":0,
    "end_minute":52,
    "formation_name":"3412",
    "slot":1,
    "player_id":422916,
    "jersey_number":1,
    "x":5.0,
    "y":0.0
  },
  {
    "match_id":1913898,
    "team_side":"away",
    "team_id":833,
    "period":16,
    "start_minute":0,
    "end_minute":52,
    "formation_name":"3412",
    "slot":2,
    "player_id":509876,
    "jersey_number":15,
    "x":1.0,
    "y":5.0
  },
  {
    "match_id":1913898,
    "team_side":"away",
    "team_id":833,
    "period":16,
    "start_minute":0,
    "end_minute":52,
    "formation_name":"3412",
    "slot":3,
    "player_id":390240,
    "jersey_number":11,
    "x":9.0,
    "y":5.0
  },
  {
    "match_id":1913898,
    "team_side":"away",
    "team_id":833,
    "period":16,
    "start_minute":0,
    "end_minute":52,
    "formation_name":"3412",
    "slot":4,
    "player_id":108100,
    "jersey_number":6,
    "x":8.0,
    "y":2.5
  },
  {
    "match_id":1913898,
    "team_side":"away",
    "team_id":833,
    "period":16,
    "start_minute":0,
    "end_minute":52,
    "formation_name":"3412",
    "slot":5,
    "player_id":423282,
    "jersey_number":22,
    "x":5.0,
    "y":2.5
  },
  {
    "match_id":1913898,
    "team_side":"away",
    "team_id":833,
    "period":16,
    "start_minute":0,
    "end_minute":52,
    "formation_name":"3412",
    "slot":6,
    "player_id":408347,
    "jersey_number":18,
    "x":2.0,
    "y":2.5
  },
  {
    "match_id":1913898,
    "team_side":"away",
    "team_id":833,
    "period":16,
    "start_minute":0,
    "end_minute":52,
    "formation_name":"3412",
    "slot":7,
    "player_id":448050,
    "jersey_number":8,
    "x":3.5,
    "y":5.0
  },
  {
    "match_id":1913898,
    "team_side":"away",
    "team_id":833,
    "period":16,
    "start_minute":0,
    "end_minute":52,
    "formation_name":"3412",
    "slot":8,
    "player_id":381643,
    "jersey_number":14,
    "x":6.5,
    "y":5.0
  },
  {
    "match_id":1913898,
    "team_side":"away",
    "team_id":833,
    "period":16,
    "start_minute":0,
    "end_minute":52,
    "formation_name":"3412",
    "slot":9,
    "player_id":463938,
    "jersey_number":30,
    "x":5.0,
    "y":6.5
  },
  {
    "match_id":1913898,
    "team_side":"away",
    "team_id":833,
    "period":16,
    "start_minute":0,
    "end_minute":52,
    "formation_name":"3412",
    "slot":10,
    "player_id":460772,
    "jersey_number":20,
    "x":3.5,
    "y":9.0
  },
  {
    "match_id":1913898,
    "team_side":"away",
    "team_id":833,
    "period":16,
    "start_minute":0,
    "end_minute":52,
    "formation_name":"3412",
    "slot":11,
    "player_id":300369,
    "jersey_number":10,
    "x":6.5,
    "y":9.0
  },
  {
    "match_id":1913898,
    "team_side":"away",
    "team_id":833,
    "period":16,
    "start_minute":52,
    "end_minute":73,
    "formation_name":"3412",
    "slot":1,
    "player_id":422916,
    "jersey_number":1,
    "x":5.0,
    "y":0.0
  },
  {
    "match_id":1913898,
    "team_side":"away",
    "team_id":833,
    "period":16,
    "start_minute":52,
    "end_minute":73,
    "formation_name":"3412",
    "slot":2,
    "player_id":509876,
    "jersey_number":15,
    "x":1.0,
    "y":5.0
  },
  {
    "match_id":1913898,
    "team_side":"away",
    "team_id":833,
    "period":16,
    "start_minute":52,
    "end_minute":73,
    "formation_name":"3412",
    "slot":3,
    "player_id":390240,
    "jersey_number":11,
    "x":9.0,
    "y":5.0
  },
  {
    "match_id":1913898,
    "team_side":"away",
    "team_id":833,
    "period":16,
    "start_minute":52,
    "end_minute":73,
    "formation_name":"3412",
    "slot":4,
    "player_id":108100,
    "jersey_number":6,
    "x":8.0,
    "y":2.5
  },
  {
    "match_id":1913898,
    "team_side":"away",
    "team_id":833,
    "period":16,
    "start_minute":52,
    "end_minute":73,
    "formation_name":"3412",
    "slot":5,
    "player_id":423282,
    "jersey_number":22,
    "x":5.0,
    "y":2.5
  },
  {
    "match_id":1913898,
    "team_side":"away",
    "team_id":833,
    "period":16,
    "start_minute":52,
    "end_minute":73,
    "formation_name":"3412",
    "slot":6,
    "player_id":402862,
    "jersey_number":23,
    "x":2.0,
    "y":2.5
  },
  {
    "match_id":1913898,
    "team_side":"away",
    "team_id":833,
    "period":16,
    "start_minute":52,
    "end_minute":73,
    "formation_name":"3412",
    "slot":7,
    "player_id":448050,
    "jersey_number":8,
    "x":3.5,
    "y":5.0
  },
  {
    "match_id":1913898,
    "team_side":"away",
    "team_id":833,
    "period":16,
    "start_minute":52,
    "end_minute":73,
    "formation_name":"3412",
    "slot":8,
    "player_id":381643,
    "jersey_number":14,
    "x":6.5,
    "y":5.0
  },
  {
    "match_id":1913898,
    "team_side":"away",
    "team_id":833,
    "period":16,
    "start_minute":52,
    "end_minute":73,
    "formation_name":"3412",
    "slot":9,
    "player_id":463938,
    "jersey_number":30,
    "x":5.0,
    "y":6.5
  },
  {
    "match_id":1913898,
    "team_side":"away",
    "team_id":833,
    "period":16,
    "start_minute":52,
    "end_minute":73,
    "formation_name":"3412",
    "slot":10,
    "player_id":460772,
    "jersey_number":20,
    "x":3.5,
    "y":9.0
  },
  {
    "match_id":1913898,
    "team_side":"away",
    "team_id":833,
    "period":16,
    "start_minute":52,
    "end_minute":73,
    "formation_name":"3412",
    "slot":11,
    "player_id":300369,
    "jersey_number":10,
    "x":6.5,
    "y":9.0
  },
  {
    "match_id":1913898,
    "team_side":"away",
    "team_id":833,
    "period":16,
    "start_minute":73,
    "end_minute":74,
    "formation_name":"3412",
    "slot":1,
    "player_id":422916,
    "jersey_number":1,
    "x":5.0,
    "y":0.0
  },
  {
    "match_id":1913898,
    "team_side":"away",
    "team_id":833,
    "period":16,
    "start_minute":73,
    "end_minute":74,
    "formation_name":"3412",
    "slot":2,
    "player_id":509876,
    "jersey_number":15,
    "x":1.0,
    "y":5.0
  },
  {
    "match_id":1913898,
    "team_side":"away",
    "team_id":833,
    "period":16,
    "start_minute":73,
    "end_minute":74,
    "formation_name":"3412",
    "slot":3,
    "player_id":390240,
    "jersey_number":11,
    "x":9.0,
    "y":5.0
  },
  {
    "match_id":1913898,
    "team_side":"away",
    "team_id":833,
    "period":16,
    "start_minute":73,
    "end_minute":74,
    "formation_name":"3412",
    "slot":4,
    "player_id":108100,
    "jersey_number":6,
    "x":8.0,
    "y":2.5
  },
  {
    "match_id":1913898,
    "team_side":"away",
    "team_id":833,
    "period":16,
    "start_minute":73,
    "end_minute":74,
    "formation_name":"3412",
    "slot":5,
    "player_id":423282,
    "jersey_number":22,
    "x":5.0,
    "y":2.5
  },
  {
    "match_id":1913898,
    "team_side":"away",
    "team_id":833,
    "period":16,
    "start_minute":73,
    "end_minute":74,
    "formation_name":"3412",
    "slot":6,
    "player_id":402862,
    "jersey_number":23,
    "x":2.0,
    "y":2.5
  },
  {
    "match_id":1913898,
    "team_side":"away",
    "team_id":833,
    "period":16,
    "start_minute":73,
    "end_minute":74,
    "formation_name":"3412",
    "slot":7,
    "player_id":448050,
    "jersey_number":8,
    "x":3.5,
    "y":5.0
  },
  {
    "match_id":1913898,
    "team_side":"away",
    "team_id":833,
    "period":16,
    "start_minute":73,
    "end_minute":74,
    "formation_name":"3412",
    "slot":8,
    "player_id":381643,
    "jersey_number":14,
    "x":6.5,
    "y":5.0
  },
  {
    "match_id":1913898,
    "team_side":"away",
    "team_id":833,
    "period":16,
    "start_minute":73,
    "end_minute":74,
    "formation_name":"3412",
    "slot":9,
    "player_id":463938,
    "jersey_number":30,
    "x":5.0,
    "y":6.5
  },
  {
    "match_id":1913898,
    "team_side":"away",
    "team_id":833,
    "period":16,
    "start_minute":73,
    "end_minute":74,
    "formation_name":"3412",
    "slot":10,
    "player_id":460772,
    "jersey_number":20,
    "x":3.5,
    "y":9.0
  },
  {
    "match_id":1913898,
    "team_side":"away",
    "team_id":833,
    "period":16,
    "start_minute":73,
    "end_minute":74,
    "formation_name":"3412",
    "slot":11,
    "player_id":299460,
    "jersey_number":9,
    "x":6.5,
    "y":9.0
  },
  {
    "match_id":1913898,
    "team_side":"away",
    "team_id":833,
    "period":16,
    "start_minute":74,
    "end_minute":88,
    "formation_name":"3412",
    "slot":1,
    "player_id":422916,
    "jersey_number":1,
    "x":5.0,
    "y":0.0
  },
  {
    "match_id":1913898,
    "team_side":"away",
    "team_id":833,
    "period":16,
    "start_minute":74,
    "end_minute":88,
    "formation_name":"3412",
    "slot":2,
    "player_id":509876,
    "jersey_number":15,
    "x":1.0,
    "y":5.0
  },
  {
    "match_id":1913898,
    "team_side":"away",
    "team_id":833,
    "period":16,
    "start_minute":74,
    "end_minute":88,
    "formation_name":"3412",
    "slot":3,
    "player_id":390240,
    "jersey_number":11,
    "x":9.0,
    "y":5.0
  },
  {
    "match_id":1913898,
    "team_side":"away",
    "team_id":833,
    "period":16,
    "start_minute":74,
    "end_minute":88,
    "formation_name":"3412",
    "slot":4,
    "player_id":108100,
    "jersey_number":6,
    "x":8.0,
    "y":2.5
  },
  {
    "match_id":1913898,
    "team_side":"away",
    "team_id":833,
    "period":16,
    "start_minute":74,
    "end_minute":88,
    "formation_name":"3412",
    "slot":5,
    "player_id":423282,
    "jersey_number":22,
    "x":5.0,
    "y":2.5
  },
  {
    "match_id":1913898,
    "team_side":"away",
    "team_id":833,
    "period":16,
    "start_minute":74,
    "end_minute":88,
    "formation_name":"3412",
    "slot":6,
    "player_id":402862,
    "jersey_number":23,
    "x":2.0,
    "y":2.5
  },
  {
    "match_id":1913898,
    "team_side":"away",
    "team_id":833,
    "period":16,
    "start_minute":74,
    "end_minute":88,
    "formation_name":"3412",
    "slot":7,
    "player_id":448050,
    "jersey_number":8,
    "x":3.5,
    "y":5.0
  },
  {
    "match_id":1913898,
    "team_side":"away",
    "team_id":833,
    "period":16,
    "start_minute":74,
    "end_minute":88,
    "formation_name":"3412",
    "slot":8,
    "player_id":381643,
    "jersey_number":14,
    "x":6.5,
    "y":5.0
  },
  {
    "match_id":1913898,
    "team_side":"away",
    "team_id":833,
    "period":16,
    "start_minute":74,
    "end_minute":88,
    "formation_name":"3412",
    "slot":9,
    "player_id":438351,
    "jersey_number":16,
    "x":5.0,
    "y":6.5
  },
  {
    "match_id":1913898,
    "team_side":"away",
    "team_id":833,
    "period":16,
    "start_minute":74,
    "end_minute":88,
    "formation_name":"3412",
    "slot":10,
    "player_id":460772,
    "jersey_number":20,
    "x":3.5,
    "y":9.0
  },
  {
    "match_id":1913898,
    "team_side":"away",
    "team_id":833,
    "period":16,
    "start_minute":74,
    "end_minute":88,
    "formation_name":"3412",
    "slot":11,
    "player_id":299460,
    "jersey_number":9,
    "x":6.5,
    "y":9.0
  },
  {
    "match_id":1913898,
    "team_side":"away",
    "team_id":833,
    "period":16,
    "start_minute":88,
    "end_minute":92,
    "formation_name":"3412",
    "slot":1,
    "player_id":422916,
    "jersey_number":1,
    "x":5.0,
    "y":0.0
  },
  {
    "match_id":1913898,
    "team_side":"away",
    "team_id":833,
    "period":16,
    "start_minute":88,
    "end_minute":92,
    "formation_name":"3412",
    "slot":2,
    "player_id":509876,
    "jersey_number":15,
    "x":1.0,
    "y":5.0
  },
  {
    "match_id":1913898,
    "team_side":"away",
    "team_id":833,
    "period":16,
    "start_minute":88,
    "end_minute":92,
    "formation_name":"3412",
    "slot":3,
    "player_id":390240,
    "jersey_number":11,
    "x":9.0,
    "y":5.0
  },
  {
    "match_id":1913898,
    "team_side":"away",
    "team_id":833,
    "period":16,
    "start_minute":88,
    "end_minute":92,
    "formation_name":"3412",
    "slot":4,
    "player_id":301330,
    "jersey_number":21,
    "x":8.0,
    "y":2.5
  },
  {
    "match_id":1913898,
    "team_side":"away",
    "team_id":833,
    "period":16,
    "start_minute":88,
    "end_minute":92,
    "formation_name":"3412",
    "slot":5,
    "player_id":423282,
    "jersey_number":22,
    "x":5.0,
    "y":2.5
  },
  {
    "match_id":1913898,
    "team_side":"away",
    "team_id":833,
    "period":16,
    "start_minute":88,
    "end_minute":92,
    "formation_name":"3412",
    "slot":6,
    "player_id":402862,
    "jersey_number":23,
    "x":2.0,
    "y":2.5
  },
  {
    "match_id":1913898,
    "team_side":"away",
    "team_id":833,
    "period":16,
    "start_minute":88,
    "end_minute":92,
    "formation_name":"3412",
    "slot":7,
    "player_id":448050,
    "jersey_number":8,
    "x":3.5,
    "y":5.0
  },
  {
    "match_id":1913898,
    "team_side":"away",
    "team_id":833,
    "period":16,
    "start_minute":88,
    "end_minute":92,
    "formation_name":"3412",
    "slot":8,
    "player_id":381643,
    "jersey_number":14,
    "x":6.5,
    "y":5.0
  },
  {
    "match_id":1913898,
    "team_side":"away",
    "team_id":833,
    "period":16,
    "start_minute":88,
    "end_minute":92,
    "formation_name":"3412",
    "slot":9,
    "player_id":438351,
    "jersey_number":16,
    "x":5.0,
    "y":6.5
  },
  {
    "match_id":1913898,
    "team_side":"away",
    "team_id":833,
    "period":16,
    "start_minute":88,
    "end_minute":92,
    "formation_name":"3412",
    "slot":10,
    "player_id":460772,
    "jersey_number":20,
    "x":3.5,
    "y":9.0
  },
  {
    "match_id":1913898,
    "team_side":"away",
    "team_id":833,
    "period":16,
    "start_minute":88,
    "end_minute":92,
    "formation_name":"3412",
    "slot":11,
    "player_id":299460,
    "jersey_number":9,
    "x":6.5,
    "y":9.0
  },
  {
    "match_id":1913898,
    "team_side":"away",
    "team_id":833,
    "period":16,
    "start_minute":92,
    "end_minute":97,
    "formation_name":"3412",
    "slot":1,
    "player_id":422916,
    "jersey_number":1,
    "x":5.0,
    "y":0.0
  },
  {
    "match_id":1913898,
    "team_side":"away",
    "team_id":833,
    "period":16,
    "start_minute":92,
    "end_minute":97,
    "formation_name":"3412",
    "slot":2,
    "player_id":509876,
    "jersey_number":15,
    "x":1.0,
    "y":5.0
  },
  {
    "match_id":1913898,
    "team_side":"away",
    "team_id":833,
    "period":16,
    "start_minute":92,
    "end_minute":97,
    "formation_name":"3412",
    "slot":3,
    "player_id":390240,
    "jersey_number":11,
    "x":9.0,
    "y":5.0
  },
  {
    "match_id":1913898,
    "team_side":"away",
    "team_id":833,
    "period":16,
    "start_minute":92,
    "end_minute":97,
    "formation_name":"3412",
    "slot":4,
    "player_id":301330,
    "jersey_number":21,
    "x":8.0,
    "y":2.5
  },
  {
    "match_id":1913898,
    "team_side":"away",
    "team_id":833,
    "period":16,
    "start_minute":92,
    "end_minute":97,
    "formation_name":"3412",
    "slot":5,
    "player_id":423282,
    "jersey_number":22,
    "x":5.0,
    "y":2.5
  },
  {
    "match_id":1913898,
    "team_side":"away",
    "team_id":833,
    "period":16,
    "start_minute":92,
    "end_minute":97,
    "formation_name":"3412",
    "slot":6,
    "player_id":402862,
    "jersey_number":23,
    "x":2.0,
    "y":2.5
  },
  {
    "match_id":1913898,
    "team_side":"away",
    "team_id":833,
    "period":16,
    "start_minute":92,
    "end_minute":97,
    "formation_name":"3412",
    "slot":7,
    "player_id":419616,
    "jersey_number":5,
    "x":3.5,
    "y":5.0
  },
  {
    "match_id":1913898,
    "team_side":"away",
    "team_id":833,
    "period":16,
    "start_minute":92,
    "end_minute":97,
    "formation_name":"3412",
    "slot":8,
    "player_id":381643,
    "jersey_number":14,
    "x":6.5,
    "y":5.0
  },
  {
    "match_id":1913898,
    "team_side":"away",
    "team_id":833,
    "period":16,
    "start_minute":92,
    "end_minute":97,
    "formation_name":"3412",
    "slot":9,
    "player_id":438351,
    "jersey_number":16,
    "x":5.0,
    "y":6.5
  },
  {
    "match_id":1913898,
    "team_side":"away",
    "team_id":833,
    "period":16,
    "start_minute":92,
    "end_minute":97,
    "formation_name":"3412",
    "slot":10,
    "player_id":460772,
    "jersey_number":20,
    "x":3.5,
    "y":9.0
  },
  {
    "match_id":1913898,
    "team_side":"away",
    "team_id":833,
    "period":16,
    "start_minute":92,
    "end_minute":97,
    "formation_name":"3412",
    "slot":11,
    "player_id":299460,
    "jersey_number":9,
    "x":6.5,
    "y":9.0
  },
  {
    "match_id":1913898,
    "team_side":"home",
    "team_id":63,
    "period":16,
    "start_minute":0,
    "end_minute":74,
    "formation_name":"442",
    "slot":1,
    "player_id":76662,
    "jersey_number":13,
    "x":5.0,
    "y":0.0
  },
  {
    "match_id":1913898,
    "team_side":"home",
    "team_id":63,
    "period":16,
    "start_minute":0,
    "end_minute":74,
    "formation_name":"442",
    "slot":2,
    "player_id":254582,
    "jersey_number":14,
    "x":1.0,
    "y":2.5
  },
  {
    "match_id":1913898,
    "team_side":"home",
    "team_id":63,
    "period":16,
    "start_minute":0,
    "end_minute":74,
    "formation_name":"442",
    "slot":3,
    "player_id":402046,
    "jersey_number":3,
    "x":9.0,
    "y":2.5
  },
  {
    "match_id":1913898,
    "team_side":"home",
    "team_id":63,
    "period":16,
    "start_minute":0,
    "end_minute":74,
    "formation_name":"442",
    "slot":4,
    "player_id":379230,
    "jersey_number":5,
    "x":3.5,
    "y":6.0
  },
  {
    "match_id":1913898,
    "team_side":"home",
    "team_id":63,
    "period":16,
    "start_minute":0,
    "end_minute":74,
    "formation_name":"442",
    "slot":5,
    "player_id":367008,
    "jersey_number":24,
    "x":3.5,
    "y":2.5
  },
  {
    "match_id":1913898,
    "team_side":"home",
    "team_id":63,
    "period":16,
    "start_minute":0,
    "end_minute":74,
    "formation_name":"442",
    "slot":6,
    "player_id":362779,
    "jersey_number":17,
    "x":6.5,
    "y":2.5
  },
  {
    "match_id":1913898,
    "team_side":"home",
    "team_id":63,
    "period":16,
    "start_minute":0,
    "end_minute":74,
    "formation_name":"442",
    "slot":7,
    "player_id":422918,
    "jersey_number":20,
    "x":1.0,
    "y":6.0
  },
  {
    "match_id":1913898,
    "team_side":"home",
    "team_id":63,
    "period":16,
    "start_minute":0,
    "end_minute":74,
    "formation_name":"442",
    "slot":8,
    "player_id":434138,
    "jersey_number":8,
    "x":6.5,
    "y":6.0
  },
  {
    "match_id":1913898,
    "team_side":"home",
    "team_id":63,
    "period":16,
    "start_minute":0,
    "end_minute":74,
    "formation_name":"442",
    "slot":9,
    "player_id":365409,
    "jersey_number":19,
    "x":6.5,
    "y":9.0
  },
  {
    "match_id":1913898,
    "team_side":"home",
    "team_id":63,
    "period":16,
    "start_minute":0,
    "end_minute":74,
    "formation_name":"442",
    "slot":10,
    "player_id":302497,
    "jersey_number":9,
    "x":3.5,
    "y":9.0
  },
  {
    "match_id":1913898,
    "team_side":"home",
    "team_id":63,
    "period":16,
    "start_minute":0,
    "end_minute":74,
    "formation_name":"442",
    "slot":11,
    "player_id":361732,
    "jersey_number":11,
    "x":9.0,
    "y":6.0
  },
  {
    "match_id":1913898,
    "team_side":"home",
    "team_id":63,
    "period":16,
    "start_minute":74,
    "end_minute":74,
    "formation_name":"442",
    "slot":1,
    "player_id":76662,
    "jersey_number":13,
    "x":5.0,
    "y":0.0
  },
  {
    "match_id":1913898,
    "team_side":"home",
    "team_id":63,
    "period":16,
    "start_minute":74,
    "end_minute":74,
    "formation_name":"442",
    "slot":1,
    "player_id":76662,
    "jersey_number":13,
    "x":5.0,
    "y":0.0
  },
  {
    "match_id":1913898,
    "team_side":"home",
    "team_id":63,
    "period":16,
    "start_minute":74,
    "end_minute":81,
    "formation_name":"442",
    "slot":1,
    "player_id":76662,
    "jersey_number":13,
    "x":5.0,
    "y":0.0
  },
  {
    "match_id":1913898,
    "team_side":"home",
    "team_id":63,
    "period":16,
    "start_minute":74,
    "end_minute":74,
    "formation_name":"442",
    "slot":2,
    "player_id":254582,
    "jersey_number":14,
    "x":1.0,
    "y":2.5
  },
  {
    "match_id":1913898,
    "team_side":"home",
    "team_id":63,
    "period":16,
    "start_minute":74,
    "end_minute":74,
    "formation_name":"442",
    "slot":2,
    "player_id":254582,
    "jersey_number":14,
    "x":1.0,
    "y":2.5
  },
  {
    "match_id":1913898,
    "team_side":"home",
    "team_id":63,
    "period":16,
    "start_minute":74,
    "end_minute":81,
    "formation_name":"442",
    "slot":2,
    "player_id":254582,
    "jersey_number":14,
    "x":1.0,
    "y":2.5
  },
  {
    "match_id":1913898,
    "team_side":"home",
    "team_id":63,
    "period":16,
    "start_minute":74,
    "end_minute":74,
    "formation_name":"442",
    "slot":3,
    "player_id":402046,
    "jersey_number":3,
    "x":9.0,
    "y":2.5
  },
  {
    "match_id":1913898,
    "team_side":"home",
    "team_id":63,
    "period":16,
    "start_minute":74,
    "end_minute":74,
    "formation_name":"442",
    "slot":3,
    "player_id":402046,
    "jersey_number":3,
    "x":9.0,
    "y":2.5
  },
  {
    "match_id":1913898,
    "team_side":"home",
    "team_id":63,
    "period":16,
    "start_minute":74,
    "end_minute":81,
    "formation_name":"442",
    "slot":3,
    "player_id":402046,
    "jersey_number":3,
    "x":9.0,
    "y":2.5
  },
  {
    "match_id":1913898,
    "team_side":"home",
    "team_id":63,
    "period":16,
    "start_minute":74,
    "end_minute":74,
    "formation_name":"442",
    "slot":4,
    "player_id":80241,
    "jersey_number":7,
    "x":3.5,
    "y":6.0
  },
  {
    "match_id":1913898,
    "team_side":"home",
    "team_id":63,
    "period":16,
    "start_minute":74,
    "end_minute":74,
    "formation_name":"442",
    "slot":4,
    "player_id":80241,
    "jersey_number":7,
    "x":3.5,
    "y":6.0
  },
  {
    "match_id":1913898,
    "team_side":"home",
    "team_id":63,
    "period":16,
    "start_minute":74,
    "end_minute":81,
    "formation_name":"442",
    "slot":4,
    "player_id":80241,
    "jersey_number":7,
    "x":3.5,
    "y":6.0
  },
  {
    "match_id":1913898,
    "team_side":"home",
    "team_id":63,
    "period":16,
    "start_minute":74,
    "end_minute":74,
    "formation_name":"442",
    "slot":5,
    "player_id":367008,
    "jersey_number":24,
    "x":3.5,
    "y":2.5
  },
  {
    "match_id":1913898,
    "team_side":"home",
    "team_id":63,
    "period":16,
    "start_minute":74,
    "end_minute":74,
    "formation_name":"442",
    "slot":5,
    "player_id":367008,
    "jersey_number":24,
    "x":3.5,
    "y":2.5
  },
  {
    "match_id":1913898,
    "team_side":"home",
    "team_id":63,
    "period":16,
    "start_minute":74,
    "end_minute":81,
    "formation_name":"442",
    "slot":5,
    "player_id":367008,
    "jersey_number":24,
    "x":3.5,
    "y":2.5
  },
  {
    "match_id":1913898,
    "team_side":"home",
    "team_id":63,
    "period":16,
    "start_minute":74,
    "end_minute":74,
    "formation_name":"442",
    "slot":6,
    "player_id":362779,
    "jersey_number":17,
    "x":6.5,
    "y":2.5
  },
  {
    "match_id":1913898,
    "team_side":"home",
    "team_id":63,
    "period":16,
    "start_minute":74,
    "end_minute":74,
    "formation_name":"442",
    "slot":6,
    "player_id":362779,
    "jersey_number":17,
    "x":6.5,
    "y":2.5
  },
  {
    "match_id":1913898,
    "team_side":"home",
    "team_id":63,
    "period":16,
    "start_minute":74,
    "end_minute":81,
    "formation_name":"442",
    "slot":6,
    "player_id":362779,
    "jersey_number":17,
    "x":6.5,
    "y":2.5
  },
  {
    "match_id":1913898,
    "team_side":"home",
    "team_id":63,
    "period":16,
    "start_minute":74,
    "end_minute":74,
    "formation_name":"442",
    "slot":7,
    "player_id":422918,
    "jersey_number":20,
    "x":1.0,
    "y":6.0
  },
  {
    "match_id":1913898,
    "team_side":"home",
    "team_id":63,
    "period":16,
    "start_minute":74,
    "end_minute":74,
    "formation_name":"442",
    "slot":7,
    "player_id":422918,
    "jersey_number":20,
    "x":1.0,
    "y":6.0
  },
  {
    "match_id":1913898,
    "team_side":"home",
    "team_id":63,
    "period":16,
    "start_minute":74,
    "end_minute":81,
    "formation_name":"442",
    "slot":7,
    "player_id":422918,
    "jersey_number":20,
    "x":1.0,
    "y":6.0
  },
  {
    "match_id":1913898,
    "team_side":"home",
    "team_id":63,
    "period":16,
    "start_minute":74,
    "end_minute":74,
    "formation_name":"442",
    "slot":8,
    "player_id":434138,
    "jersey_number":8,
    "x":6.5,
    "y":6.0
  },
  {
    "match_id":1913898,
    "team_side":"home",
    "team_id":63,
    "period":16,
    "start_minute":74,
    "end_minute":74,
    "formation_name":"442",
    "slot":8,
    "player_id":434138,
    "jersey_number":8,
    "x":6.5,
    "y":6.0
  },
  {
    "match_id":1913898,
    "team_side":"home",
    "team_id":63,
    "period":16,
    "start_minute":74,
    "end_minute":81,
    "formation_name":"442",
    "slot":8,
    "player_id":434138,
    "jersey_number":8,
    "x":6.5,
    "y":6.0
  },
  {
    "match_id":1913898,
    "team_side":"home",
    "team_id":63,
    "period":16,
    "start_minute":74,
    "end_minute":74,
    "formation_name":"442",
    "slot":9,
    "player_id":365409,
    "jersey_number":19,
    "x":6.5,
    "y":9.0
  },
  {
    "match_id":1913898,
    "team_side":"home",
    "team_id":63,
    "period":16,
    "start_minute":74,
    "end_minute":74,
    "formation_name":"442",
    "slot":9,
    "player_id":365409,
    "jersey_number":19,
    "x":6.5,
    "y":9.0
  },
  {
    "match_id":1913898,
    "team_side":"home",
    "team_id":63,
    "period":16,
    "start_minute":74,
    "end_minute":81,
    "formation_name":"442",
    "slot":9,
    "player_id":365409,
    "jersey_number":19,
    "x":6.5,
    "y":9.0
  },
  {
    "match_id":1913898,
    "team_side":"home",
    "team_id":63,
    "period":16,
    "start_minute":74,
    "end_minute":74,
    "formation_name":"442",
    "slot":10,
    "player_id":302497,
    "jersey_number":9,
    "x":3.5,
    "y":9.0
  },
  {
    "match_id":1913898,
    "team_side":"home",
    "team_id":63,
    "period":16,
    "start_minute":74,
    "end_minute":74,
    "formation_name":"442",
    "slot":10,
    "player_id":302497,
    "jersey_number":9,
    "x":3.5,
    "y":9.0
  },
  {
    "match_id":1913898,
    "team_side":"home",
    "team_id":63,
    "period":16,
    "start_minute":74,
    "end_minute":81,
    "formation_name":"442",
    "slot":10,
    "player_id":371497,
    "jersey_number":22,
    "x":3.5,
    "y":9.0
  },
  {
    "match_id":1913898,
    "team_side":"home",
    "team_id":63,
    "period":16,
    "start_minute":74,
    "end_minute":74,
    "formation_name":"442",
    "slot":11,
    "player_id":361732,
    "jersey_number":11,
    "x":9.0,
    "y":6.0
  },
  {
    "match_id":1913898,
    "team_side":"home",
    "team_id":63,
    "period":16,
    "start_minute":74,
    "end_minute":74,
    "formation_name":"442",
    "slot":11,
    "player_id":375621,
    "jersey_number":4,
    "x":9.0,
    "y":6.0
  },
  {
    "match_id":1913898,
    "team_side":"home",
    "team_id":63,
    "period":16,
    "start_minute":74,
    "end_minute":81,
    "formation_name":"442",
    "slot":11,
    "player_id":375621,
    "jersey_number":4,
    "x":9.0,
    "y":6.0
  },
  {
    "match_id":1913898,
    "team_side":"home",
    "team_id":63,
    "period":16,
    "start_minute":81,
    "end_minute":81,
    "formation_name":"442",
    "slot":1,
    "player_id":76662,
    "jersey_number":13,
    "x":5.0,
    "y":0.0
  },
  {
    "match_id":1913898,
    "team_side":"home",
    "team_id":63,
    "period":16,
    "start_minute":81,
    "end_minute":82,
    "formation_name":"442",
    "slot":1,
    "player_id":76662,
    "jersey_number":13,
    "x":5.0,
    "y":0.0
  },
  {
    "match_id":1913898,
    "team_side":"home",
    "team_id":63,
    "period":16,
    "start_minute":81,
    "end_minute":81,
    "formation_name":"442",
    "slot":2,
    "player_id":254582,
    "jersey_number":14,
    "x":1.0,
    "y":2.5
  },
  {
    "match_id":1913898,
    "team_side":"home",
    "team_id":63,
    "period":16,
    "start_minute":81,
    "end_minute":82,
    "formation_name":"442",
    "slot":2,
    "player_id":254582,
    "jersey_number":14,
    "x":1.0,
    "y":2.5
  },
  {
    "match_id":1913898,
    "team_side":"home",
    "team_id":63,
    "period":16,
    "start_minute":81,
    "end_minute":81,
    "formation_name":"442",
    "slot":3,
    "player_id":369497,
    "jersey_number":21,
    "x":9.0,
    "y":2.5
  },
  {
    "match_id":1913898,
    "team_side":"home",
    "team_id":63,
    "period":16,
    "start_minute":81,
    "end_minute":82,
    "formation_name":"442",
    "slot":3,
    "player_id":369497,
    "jersey_number":21,
    "x":9.0,
    "y":2.5
  },
  {
    "match_id":1913898,
    "team_side":"home",
    "team_id":63,
    "period":16,
    "start_minute":81,
    "end_minute":81,
    "formation_name":"442",
    "slot":4,
    "player_id":80241,
    "jersey_number":7,
    "x":3.5,
    "y":6.0
  },
  {
    "match_id":1913898,
    "team_side":"home",
    "team_id":63,
    "period":16,
    "start_minute":81,
    "end_minute":82,
    "formation_name":"442",
    "slot":4,
    "player_id":80241,
    "jersey_number":7,
    "x":3.5,
    "y":6.0
  },
  {
    "match_id":1913898,
    "team_side":"home",
    "team_id":63,
    "period":16,
    "start_minute":81,
    "end_minute":81,
    "formation_name":"442",
    "slot":5,
    "player_id":367008,
    "jersey_number":24,
    "x":3.5,
    "y":2.5
  },
  {
    "match_id":1913898,
    "team_side":"home",
    "team_id":63,
    "period":16,
    "start_minute":81,
    "end_minute":82,
    "formation_name":"442",
    "slot":5,
    "player_id":367008,
    "jersey_number":24,
    "x":3.5,
    "y":2.5
  },
  {
    "match_id":1913898,
    "team_side":"home",
    "team_id":63,
    "period":16,
    "start_minute":81,
    "end_minute":81,
    "formation_name":"442",
    "slot":6,
    "player_id":362779,
    "jersey_number":17,
    "x":6.5,
    "y":2.5
  },
  {
    "match_id":1913898,
    "team_side":"home",
    "team_id":63,
    "period":16,
    "start_minute":81,
    "end_minute":82,
    "formation_name":"442",
    "slot":6,
    "player_id":362779,
    "jersey_number":17,
    "x":6.5,
    "y":2.5
  },
  {
    "match_id":1913898,
    "team_side":"home",
    "team_id":63,
    "period":16,
    "start_minute":81,
    "end_minute":81,
    "formation_name":"442",
    "slot":7,
    "player_id":422918,
    "jersey_number":20,
    "x":1.0,
    "y":6.0
  },
  {
    "match_id":1913898,
    "team_side":"home",
    "team_id":63,
    "period":16,
    "start_minute":81,
    "end_minute":82,
    "formation_name":"442",
    "slot":7,
    "player_id":303728,
    "jersey_number":16,
    "x":1.0,
    "y":6.0
  },
  {
    "match_id":1913898,
    "team_side":"home",
    "team_id":63,
    "period":16,
    "start_minute":81,
    "end_minute":81,
    "formation_name":"442",
    "slot":8,
    "player_id":434138,
    "jersey_number":8,
    "x":6.5,
    "y":6.0
  },
  {
    "match_id":1913898,
    "team_side":"home",
    "team_id":63,
    "period":16,
    "start_minute":81,
    "end_minute":82,
    "formation_name":"442",
    "slot":8,
    "player_id":434138,
    "jersey_number":8,
    "x":6.5,
    "y":6.0
  },
  {
    "match_id":1913898,
    "team_side":"home",
    "team_id":63,
    "period":16,
    "start_minute":81,
    "end_minute":81,
    "formation_name":"442",
    "slot":9,
    "player_id":365409,
    "jersey_number":19,
    "x":6.5,
    "y":9.0
  },
  {
    "match_id":1913898,
    "team_side":"home",
    "team_id":63,
    "period":16,
    "start_minute":81,
    "end_minute":82,
    "formation_name":"442",
    "slot":9,
    "player_id":365409,
    "jersey_number":19,
    "x":6.5,
    "y":9.0
  },
  {
    "match_id":1913898,
    "team_side":"home",
    "team_id":63,
    "period":16,
    "start_minute":81,
    "end_minute":81,
    "formation_name":"442",
    "slot":10,
    "player_id":371497,
    "jersey_number":22,
    "x":3.5,
    "y":9.0
  },
  {
    "match_id":1913898,
    "team_side":"home",
    "team_id":63,
    "period":16,
    "start_minute":81,
    "end_minute":82,
    "formation_name":"442",
    "slot":10,
    "player_id":371497,
    "jersey_number":22,
    "x":3.5,
    "y":9.0
  },
  {
    "match_id":1913898,
    "team_side":"home",
    "team_id":63,
    "period":16,
    "start_minute":81,
    "end_minute":81,
    "formation_name":"442",
    "slot":11,
    "player_id":375621,
    "jersey_number":4,
    "x":9.0,
    "y":6.0
  },
  {
    "match_id":1913898,
    "team_side":"home",
    "team_id":63,
    "period":16,
    "start_minute":81,
    "end_minute":82,
    "formation_name":"442",
    "slot":11,
    "player_id":375621,
    "jersey_number":4,
    "x":9.0,
    "y":6.0
  },
  {
    "match_id":1913898,
    "team_side":"home",
    "team_id":63,
    "period":2,
    "start_minute":82,
    "end_minute":97,
    "formation_name":"442",
    "slot":1,
    "player_id":76662,
    "jersey_number":13,
    "x":5.0,
    "y":0.0
  },
  {
    "match_id":1913898,
    "team_side":"home",
    "team_id":63,
    "period":2,
    "start_minute":82,
    "end_minute":97,
    "formation_name":"442",
    "slot":2,
    "player_id":303728,
    "jersey_number":16,
    "x":1.0,
    "y":2.5
  },
  {
    "match_id":1913898,
    "team_side":"home",
    "team_id":63,
    "period":2,
    "start_minute":82,
    "end_minute":97,
    "formation_name":"442",
    "slot":3,
    "player_id":369497,
    "jersey_number":21,
    "x":9.0,
    "y":2.5
  },
  {
    "match_id":1913898,
    "team_side":"home",
    "team_id":63,
    "period":2,
    "start_minute":82,
    "end_minute":97,
    "formation_name":"442",
    "slot":4,
    "player_id":80241,
    "jersey_number":7,
    "x":3.5,
    "y":6.0
  },
  {
    "match_id":1913898,
    "team_side":"home",
    "team_id":63,
    "period":2,
    "start_minute":82,
    "end_minute":97,
    "formation_name":"442",
    "slot":5,
    "player_id":367008,
    "jersey_number":24,
    "x":3.5,
    "y":2.5
  },
  {
    "match_id":1913898,
    "team_side":"home",
    "team_id":63,
    "period":2,
    "start_minute":82,
    "end_minute":97,
    "formation_name":"442",
    "slot":6,
    "player_id":362779,
    "jersey_number":17,
    "x":6.5,
    "y":2.5
  },
  {
    "match_id":1913898,
    "team_side":"home",
    "team_id":63,
    "period":2,
    "start_minute":82,
    "end_minute":97,
    "formation_name":"442",
    "slot":7,
    "player_id":254582,
    "jersey_number":14,
    "x":1.0,
    "y":6.0
  },
  {
    "match_id":1913898,
    "team_side":"home",
    "team_id":63,
    "period":2,
    "start_minute":82,
    "end_minute":97,
    "formation_name":"442",
    "slot":8,
    "player_id":434138,
    "jersey_number":8,
    "x":6.5,
    "y":6.0
  },
  {
    "match_id":1913898,
    "team_side":"home",
    "team_id":63,
    "period":2,
    "start_minute":82,
    "end_minute":97,
    "formation_name":"442",
    "slot":9,
    "player_id":365409,
    "jersey_number":19,
    "x":6.5,
    "y":9.0
  },
  {
    "match_id":1913898,
    "team_side":"home",
    "team_id":63,
    "period":2,
    "start_minute":82,
    "end_minute":97,
    "formation_name":"442",
    "slot":10,
    "player_id":371497,
    "jersey_number":22,
    "x":3.5,
    "y":9.0
  },
  {
    "match_id":1913898,
    "team_side":"home",
    "team_id":63,
    "period":2,
    "start_minute":82,
    "end_minute":97,
    "formation_name":"442",
    "slot":11,
    "player_id":375621,
    "jersey_number":4,
    "x":9.0,
    "y":6.0
  }
]